yourface
