Metadata-Version: 1.1
Name: yourface
Version: 0.1.4
Summary: import your face
Home-page: https://github.com/bbriggs/yourface
Author: Bren 'fraq' Briggs
Author-email: UNKNOWN
License: MIT
Platform: UNKNOWN
Classifier: Development Status :: 5 - Production/Stable
Classifier: License :: OSI Approved :: MIT License
Classifier: Programming Language :: Python
